<TextObjectProperties>
  <Layout>
    <Frame>
      <BorderWidth>0</BorderWidth>
      <BorderEffect>FLAT</BorderEffect>
      <Color>
        <Mode>COLORAREA_SOLID</Mode>
        <Luminosity>85</Luminosity>
        <FillDirection>COLORAREA_HORZ</FillDirection>
        <FillPattern>COLORAREA_PATTERN1</FillPattern>
        <PrimaryCol>
          <Col>
            <Red>4</Red>
            <Green>108</Green>
            <Blue>193</Blue>
            <Alpha>255</Alpha>
          </Col>
          <IsCalculated>false</IsCalculated>
          <ColorExpr></ColorExpr>
        </PrimaryCol>
        <SecondaryCol></SecondaryCol>
        <Alpha>255</Alpha>
      </Color>
      <Font>
        <FontName>Calibri</FontName>
        <PointSize1000>9000</PointSize1000>
        <Underline>false</Underline>
        <Bold>false</Bold>
        <Italic>false</Italic>
        <DropShadow>false</DropShadow>
      </Font>
      <CaptionFont>
        <FontName>Tahoma</FontName>
        <PointSize1000>10000</PointSize1000>
        <Underline>false</Underline>
        <Bold>true</Bold>
        <Italic>false</Italic>
        <DropShadow>false</DropShadow>
      </CaptionFont>
      <Name></Name>
      <Detached>false</Detached>
      <AllowMinimize>false</AllowMinimize>
      <AutoMinimize>false</AutoMinimize>
      <AllowMaximize>false</AllowMaximize>
      <AllowInfo>false</AllowInfo>
      <PrintIcon>false</PrintIcon>
      <CopyIcon>false</CopyIcon>
      <XLIcon>false</XLIcon>
      <SearchIcon>false</SearchIcon>
      <SelectPossibleIcon>false</SelectPossibleIcon>
      <SelectExcludedIcon>false</SelectExcludedIcon>
      <SelectAllIcon>false</SelectAllIcon>
      <ClearIcon>false</ClearIcon>
      <ClearOtherIcon>false</ClearOtherIcon>
      <LockIcon>false</LockIcon>
      <HelpText></HelpText>
      <ObjectId></ObjectId>
      <ShrinkFrameToData>true</ShrinkFrameToData>
      <ShowCaption>false</ShowCaption>
      <MultiLine>0</MultiLine>
      <ActiveBgColor>
        <Mode>COLORAREA_SOLID</Mode>
        <Luminosity>85</Luminosity>
        <FillDirection>COLORAREA_HORZ</FillDirection>
        <FillPattern>COLORAREA_PATTERN1</FillPattern>
        <PrimaryCol>
          <Col>
            <Red>210</Red>
            <Green>210</Green>
            <Blue>210</Blue>
            <Alpha>255</Alpha>
          </Col>
          <IsCalculated>false</IsCalculated>
          <ColorExpr></ColorExpr>
        </PrimaryCol>
        <SecondaryCol>
          <Col>
            <Red>153</Red>
            <Green>153</Green>
            <Blue>153</Blue>
            <Alpha>255</Alpha>
          </Col>
          <IsCalculated>false</IsCalculated>
          <ColorExpr></ColorExpr>
        </SecondaryCol>
        <Alpha>255</Alpha>
      </ActiveBgColor>
      <BgColor>
        <Mode>COLORAREA_SOLID</Mode>
        <Luminosity>85</Luminosity>
        <FillDirection>COLORAREA_HORZ</FillDirection>
        <FillPattern>COLORAREA_PATTERN1</FillPattern>
        <PrimaryCol>
          <Col>
            <Red>232</Red>
            <Green>232</Green>
            <Blue>232</Blue>
            <Alpha>255</Alpha>
          </Col>
          <IsCalculated>false</IsCalculated>
          <ColorExpr></ColorExpr>
        </PrimaryCol>
        <SecondaryCol>
          <Col>
            <Red>200</Red>
            <Green>200</Green>
            <Blue>200</Blue>
            <Alpha>255</Alpha>
          </Col>
          <IsCalculated>false</IsCalculated>
          <ColorExpr></ColorExpr>
        </SecondaryCol>
        <Alpha>255</Alpha>
      </BgColor>
      <ActiveFgColor>
        <Mode>COLORAREA_SOLID</Mode>
        <Luminosity>85</Luminosity>
        <FillDirection>COLORAREA_HORZ</FillDirection>
        <FillPattern>COLORAREA_PATTERN1</FillPattern>
        <PrimaryCol>
          <Col>
            <Red>54</Red>
            <Green>54</Green>
            <Blue>54</Blue>
            <Alpha>255</Alpha>
          </Col>
          <IsCalculated>false</IsCalculated>
          <ColorExpr></ColorExpr>
        </PrimaryCol>
        <SecondaryCol></SecondaryCol>
        <Alpha>255</Alpha>
      </ActiveFgColor>
      <FgColor>
        <Mode>COLORAREA_SOLID</Mode>
        <Luminosity>85</Luminosity>
        <FillDirection>COLORAREA_HORZ</FillDirection>
        <FillPattern>COLORAREA_PATTERN1</FillPattern>
        <PrimaryCol>
          <Col>
            <Red>54</Red>
            <Green>54</Green>
            <Blue>54</Blue>
            <Alpha>255</Alpha>
          </Col>
          <IsCalculated>false</IsCalculated>
          <ColorExpr></ColorExpr>
        </PrimaryCol>
        <SecondaryCol></SecondaryCol>
        <Alpha>255</Alpha>
      </FgColor>
      <FixCorner>true</FixCorner>
      <FixCornerSize>21</FixCornerSize>
      <RelCornerSize>4059000000000000</RelCornerSize>
      <Power>4000000000000000</Power>
      <RoundedShape>true</RoundedShape>
      <EnableTopLeftRounded>true</EnableTopLeftRounded>
      <EnableTopRightRounded>true</EnableTopRightRounded>
      <EnableBottomLeftRounded>true</EnableBottomLeftRounded>
      <EnableBottomRightRounded>true</EnableBottomRightRounded>
      <Light>3FEE666666666666</Light>
      <Dark>3FC3333333333333</Dark>
      <Rainbow>false</Rainbow>
      <TextAdjustHorizontal>0</TextAdjustHorizontal>
      <TextAdjustVertical>4</TextAdjustVertical>
      <Show></Show>
      <AllowMoveSize>true</AllowMoveSize>
      <AllowCopyClone>true</AllowCopyClone>
      <dummy></dummy>
      <CustomObjectGuid enctype="base64"></CustomObjectGuid>
      <CustomObjectProperties enctype="base64"></CustomObjectProperties>
      <ScrollBkgColor>
        <Col>
          <Red>255</Red>
          <Green>255</Green>
          <Blue>255</Blue>
          <Alpha>255</Alpha>
        </Col>
        <IsCalculated>false</IsCalculated>
        <ColorExpr></ColorExpr>
      </ScrollBkgColor>
      <ScrollButtonColor>
        <Col>
          <Red>192</Red>
          <Green>192</Green>
          <Blue>192</Blue>
          <Alpha>255</Alpha>
        </Col>
        <IsCalculated>false</IsCalculated>
        <ColorExpr></ColorExpr>
      </ScrollButtonColor>
      <ScrollStyle>SCROLL_SIX</ScrollStyle>
      <ScrollWidth>38</ScrollWidth>
      <AllowModify>true</AllowModify>
      <CopyImageIcon>false</CopyImageIcon>
      <PreserveScrollPosition>false</PreserveScrollPosition>
      <ShadowIntensity>SHADOW_NONE</ShadowIntensity>
      <OnActivateActionItems></OnActivateActionItems>
      <OnDeactivateActionItems></OnDeactivateActionItems>
      <Extension></Extension>
      <Background></Background>
      <MenuIcon>false</MenuIcon>
      <ExtendedProperties></ExtendedProperties>
      <ExtendedValues></ExtendedValues>
      <StateName></StateName>
    </Frame>
    <LegacyHelpModeThatHasNoEffectWhatSoEver>false</LegacyHelpModeThatHasNoEffectWhatSoEver>
    <TextAdjustHorizontal>1</TextAdjustHorizontal>
    <TextAdjustVertical>4</TextAdjustVertical>
    <TopMargin>10</TopMargin>
    <BottomMargin>10</BottomMargin>
    <LeftMargin>10</LeftMargin>
    <RightMargin>10</RightMargin>
    <TextColor></TextColor>
    <BkgColor>
      <Mode>COLORAREA_SOLID</Mode>
      <Luminosity>85</Luminosity>
      <FillDirection>COLORAREA_HORZ</FillDirection>
      <FillPattern>COLORAREA_PATTERN1</FillPattern>
      <PrimaryCol>
        <Col>
          <Red>214</Red>
          <Green>231</Green>
          <Blue>248</Blue>
          <Alpha>255</Alpha>
        </Col>
        <IsCalculated>false</IsCalculated>
        <ColorExpr></ColorExpr>
      </PrimaryCol>
      <SecondaryCol></SecondaryCol>
      <Alpha>255</Alpha>
    </BkgColor>
    <BkgImageSettings></BkgImageSettings>
    <BkgMode>BKG_IMAGE</BkgMode>
    <Bmp enctype="base64">
        iVBORw0KGgoAAAANSUhEUgAAAoAAAAFACAYAAAAszc0KAABNRUlEQVR42u3deXycV3kv8N9zznln
        lSzJtuQ9XrEd29kXkhAS9rKUhJ3SUmjvpZc2cLtSuO1tS+h+oRstpeW2t2UtJayBUnZKAiQhe2LH
        sRPHjuPdsrXP+r7nPPePd0ZWHGs0crzI9u/7+Qg5tjQajUa8v3nOeZ4DEBERERERERERERERERER
        ERERERERERERERERERERERERERERERERERERERERERERERERERERERERERERERERERERERERERER
        ERERERERERERERERERERERERERERERERERERERERERERERERERERERERERERERERERERERERERER
        ERERERERERERERERERERERERERERERERERERERERERERERERERERERERERERERERERERERERERER
        ERERERERERERERERERERERERERERERERERERERERERERERERERERERERERERERERERERERERERER
        ERERERERERERERERERERERERERERERERERERERHROUiccxARPhInlUIbjzc0Sd8DpvGeiIjo3L1A
        AgGAQhwAqAC8PJ7sB12Vj/DJCNWN93bCnxWAb7wnIiKiya+hx7p+gtfQE/xA33LLLSgUCnwkjvOF
        i8ILAKuAWGQUEiVWOmBMB0QFgizqfh+8liAwGCh9HarxEpFobjXePndg7Ou9xuQXAKEPQBFAFkC+
        8T7Hl0FERHTGXiSBKoAagErjfQkwB0Oo7Jvd8ar+XLTikGp8SCTaNbv4KigCrBSRsQugqEFFEcIY
        vI4BGjuPukgjFEp66eWjfBzK5TJElYH6Wbw6iY/9IcMAnthQxecuCEguH/P3rK7GO5dak1teibd3
        CBSAgcABYiEwfFSJiOgcSoYBUA9FAiBAIchHK8Z8qO7IRUt3dtgrHjNw9+bw5o3Ayk1A12Q3FYGr
        bMcXZuI4BkNgK0EUwQpEjMl5axCaLzh8AoxW70c1eeKygdEvXjdY/q+X1pODF8YBi3w4khLFAM4A
        CoGVfPoXfMISEdE5nkHQvFRqgNcKBIokABqOXCStASKDPRnX93BP4YXfmd35+ttzbuV9nblLYd14
        ooQPMCFUrUJVYDxgeH2d7IEXYQVw8tCnVmCfUeUr1x6W4coPXzBY/sbrRso/uK6alC7UcCTkGZOF
        QRZinEI1gQhUA6BBFDBAkAlPfCIionNdI4gYFSBAjIoYQBUQcRoSCaghhNp4OBQD5Fzx4VmFF9ze
        U3jFl7ryz/9BIXvh0YEmUngVCMPgsUIgA+CR55/CG4GzE0Nf7PsxUvnxmv7Rz75uYOyrr6356hUa
        0lckzhgYU4QxERA0DggCaDPkMeARERGdkIBoFJBgYBRGohBihFBCEgJ8IxBmbe6e2R03fLm38y1f
        mpV/3tbI9h4VBhMvsIGXZwbA8dAHiBXYCaHvIA6N3HLBwdFPvW2ofPdbvGKRlacFvoCgPsALECzD
        HhER0SkPhd7AKozYEGIzHggVsII93YUrP9vX+fOfnDvrTRsj2zfhE30E6DkfBs/RAKhQeCdwE9vL
        sX/on1buG/m/vzxavfftiUevFSDj8jCSB1RjBj4iIqIZHghFoqAV1JMKvALOor8zd/knFsz6H/84
        v/uXnpjwOVaRiMAm5+Jl/RwLgEFU1YrYpPk3o9V7i7sH//S/D5a++Su1uLLWPCP0JTZd1iUiIqIz
        JN4EA+cnhsGgQDbKb+kpvvwfFvf87v/rzF1eGk+P6p3IubVX8JwIgIpEoMaJmPFl3v3D/7xh56Hf
        /71KvP/NUCCyDsZ0AJAY8BYIpzT0cSsmERGdE8HjlBfbTACsBzQKYQyxTwt++Wj+55bO/aM/nt/1
        jk1HrsUhgoSksULIAHgmBz+Bc2g0dfgwhB39v/f6/cP/9w/qSXyhs4AzsyDiYtVEgOBO5v0JocXT
        06SbWJ/xe8HFZiIiOjMvws/4Tw1TXwtPchhMRJyqJlESRpB4IOOih+d3/Y8/XN77x1+0prv5gZEi
        OauD4FkaAIMAxgJIAGCs+iD2j3z83XsPf/jmJGBOxlkY0wlAE6g/oXv6FABCerAh0Djw1zZGxDjA
        ukbQk8YbgBAE3gPBp5VAbdwQq4JERHRGh4zGTAxp/NlYwFrAGE0DYeNapyGdrRsSpKNe/NOvozAn
        vB6iEOsBcSGMop54OIPDC+f82s3zZ/3CRzpyFzc/zqVX57NvafgsC4ABqsGKOA8Ao9V7sP3Ab/7W
        obEfvR+CzqzLwEhHUE3Ciar2Pe2VjADOAlEE2AiwjfNq6nVBrRZQGgMqY4qxUWB0RFEtKypVoF4L
        qFUFcT29PU0HWiL4wP/3ICKiM5axBrZR9DAGiDJANqfIZA3yOSBXEHTOEnR0AvkOQbEDyGYNMhmF
        APAK+BiIYyA56uiEE1ctNImIM0HHTC2pA4rRuR3XfmDFvL/6y87cFWla1MSKGI+z6OSusyQAKlTV
        iZgEAOLkIDbteu2vHS7d8efWIJdxnTCIfEiXec2z+0pHJpQbk4a9KJMGv6BArSoYHAgYHlAcPqQY
        OKwYGlRUSgFJ40kMyHgFEI1fiubbkecjeEAcERGd4WUZHCnlNYomzbfmSpc2lr2iCHARkC8adPcI
        Zs8RzJkr6Jot6JltkM0pjKRBMK6n19MQjpy49ewrhCYYcRoQ23oyCh9QnVO85n9tWPLlD0eurxEE
        gxORs6Jr+IwPgOnwZqsANPED2HHo/W/aM/CRj4SA3qzrBOC8IhY8mzylabhrVvgymTT4eRWMDQf0
        9yv69ysO7lMMHFKUSwFJLBDTGBgdpUu/4yFPcOwD4PQYvzhERERnqGdceI+VmxrXxGYw9AmQxOlK
        mAbARYpC0WD2XEHfAkHvfEFvr6Cjy8CKIo6Bev1IhdA8+6MYgiBSILG1ZBTGoH/R7He/e/ncD9zi
        7Ow0O8FLOkeQAfA0va4wDo19fnsGP3rN1j3v+pgP2JCNsrAmH9LGjuN7GjQrfYI0vOVy6VerlAWH
        Dwbs2R2wZ1fA4YMB1YpAgfFXL849vZrXvC0iIiKaIpgcVc0LAUgaoTCO03/L5RVz+gwWLTFYtNhg
        Tp9BvqAICVCtpiFS8awrgyri1IeKqcU1WINNaxb9/TsX9dx0R+PfXbpr8cxcrzsjA6BqMCImAMBI
        5d7C5t1v+JeRys4356IMjO1QDYke71Jvc0+fc0A2l25WLZcFB/Z4PLktYPdTitGRAFV52vIvDI5U
        Ctm8QUREdALTyoTKXnj6MrCIonOWweLzBMtWGcxbZFEoKLwHatU0PALPZs+gCWKcBD8m1biOWfml
        n1u3+Av/bVb+8vLRmYQB8KQJaHT3+sQPYOu+X3nn7sO3/GPGApHrhqpPAD2u5g4N6RMrmwOyGaBW
        E+zd7bFta8DeXYrRsQADQSYHRI1O3omB8YQ/0wHIhNct6dfjTBgiIprZFPq0PUw6XhU5sXmjGeg0
        AHEC1KtAgKKzw2DhEsGqNQYLF1tks4paPQ2D0CPX7+O4Nici1sXJEOoeWDznTb+8ZsE/fKyxLGwb
        3cIMgCf8CaWJEXEBAPYc/sjKLXv/55cDcEHOdQCwXuHtcTxLEZDu08vnARHB4f6AbY8FPLktYPBw
        gDGCTDZd3hVzZOPqs3vUBQbNDpAJoU8VIXgoPDQoFNp4fyRoBi4lExHRDGXM05syxAgEkr4XCyP2
        qPXd9GIcnu3ss0ZDpYa0KlivASEoeuYYLFtlsGq1wZxeA1VFpZLuLzzeuorAesDbajIGA2xcu/Dv
        XrtozrufODqrMACegNcSULEQ+IA6Nu/82ffsGvjihwqZLIzJq2pyXD9CDYDLpHv7kljw1A6PzZsS
        7N+Tjn7MZYEom3bqNrt+j/PXofEqJf0lCPDwSQIfPLxHOv8vHHneO3dkD6ERC+cysDYL5zKIbBbW
        ZeFMhi3CREQ0c67UQZH4OnxSRxJqSJIavK8jSeoIwSNoYx9fczlW0pBobbqNyhgL6xwMbKNiqAjH
        WfFoBlBVIK4B1RrgnGL+IsG6DQ7nLbdwkaJaBZL6cVcEVcQhhIqU6zUsmf3631639N/+wiADKCxE
        /UxftZvRAVARRBrDF/uHb523ec9bv1qtj12Zz3ZD1XtA7TRvcDz45QtAaUyxbWvAY5sDBg9p2uyR
        bbSWhMZ+vmk/ogbmyIRnJD5GkgTESaNdXdKvkc91olCci47CXMzqnI+uWQvR2TEfHcU+FPOzEUU5
        GBPBiIUYk74XC2MMxFjuMyQiohmUJoCgHuo9ggaoeoTQeO/riJMqxioDKI31Y3h0H0ZG92Bk7ABK
        pUMYKx1CtTqGaj29ThsDZBxgIwdnogl77MO0q4SmMQMkJGkQ9AnQM1ewep3BqjUGxQ5BpTwhCE47
        s4kXsbZSG0Iu03H3ukWfvqG368YDR2cYBsDpZLUJmyo3737723ce/OTHs5HA2W5VjTHdH5Nq2qGb
        ywPlUcWWRwK2bEowOirpvr9seovH060rxkAgUA2I4xrqcVrZA9Lb7e7sxZzZKzGv93z09a7G7O7l
        yGVmwbksIpdNl3jVQ9U3Xi3FjVc+IX2ua0BAGD9mJJ2rxARIREQzhJHGwpRp7G5KzzdNz/01MMbA
        mAjOZSDiYBpltySpIklqqFSHMTC8Awf7t+JA/xYcGtiO4dFDqNfTm3c2XZWLbD5dmYNCp1khlEaQ
        rNXS/YCdnYq1GxzWrjcodAqqlbTT+DjOKlaRCIkfklqsWNr3tl9Yt/gTnzg6yzAAtscC8HFyCD/Z
        dtmnRytP/Vwh0wnATHuvX/Dpkmq+AxgbFWzdlOCxTQFjpYB8wSCTwfSrfQIYpHcjaIx6PUY9Tv+p
        WMxg4bx1mDd3PfrmrkZPzzJ0FufCRQWIKmJfQxJX4BshL4QER8p56bPOHLNViWu+RER0pnhm5nn6
        km46XNcYly7/GgcXFRDZDFQEcVzBaOkABgZ24OChx3Dg4Gbs69+McjldQ85EQCaThbHpKQxHiiRt
        ZVXApLMDK+WAjqLB6g0GazY4dHQqKmPpUrWZZmdBujcw2HJ9FJ358z7z3FX3vTVyc8czDQNgqwiN
        AEl3zIWDQ18878En3/ADESzPuG6oJoppVP00pGfwFgppq/iWjQGbHk5QLgnyhTQUTvdbN8ZAIfBJ
        DbW6R+LTjuDZ3fOxeMGlOG/xlZjfuw7FwhwACu/rqCcVJL6GkCRofgPS6GU/0uUrE34hiIiIzh1H
        9vwpkOYAGBfB2SwyLgdrMwCAsVI/9vc/gid33429ex/A4Eg/4iStDmYzDtZlINPcOyiShr1KGSgU
        FRsudFh7gUGUAcrl9Eziae4RVBEn9WQIqthx8bIvvKCv+/VPATCKEGQGFXNmTABUqAhEAeCRXW+9
        4cmDn7k1FzlYU/SKxE7jhqCa7vGDANsfUzx8f8DQgCJfSE/xmFYnrxgYCAIS1Gp11OtAIQ/M79uA
        8xZdjoULLsGc7qWIojySpIZqfQze1xBCSGOdMWkpnIiIiNq9lEORHg2ijQKMtTnkMkUYl0MclzAw
        8CR277sfu/bch339m1GrpZXBbDYHA9PoLG4jDDY6iNOKINA9W3DhpQYrVgug6d/JNI+VEDjvQ8lW
        4wTL+n7uxvVLPv3Vo7MOAyCOtE2HUMWmp972u7sOff5PirkOqIoHgm3/dhrLvQVg/z7FfXcG7N+j
        yOaATHZ6Fb9mo0Ucl1Gtp0+OvjlL8JzlL8SKZddiVudCAEBcL6FWLzeWcgFjnt2pc0RERHQsoVEl
        BJxxiDIFRJkiRBWDw7uxfefteHzHD3BoYB9UgWxGEEX5xv7+9lZgRdIRMrUqMH+R4LKrDeYvaDSK
        JNPdH2i8iNpSdQxL5r7xf28475N/akxuxoyKOf0BUIOFGB9CGbc9svjfSrXBtxSzXdNf8lWgUEw3
        d2683+OxzQpIOt9vOt+iMRYheFSrNSQe6OwoYPmSq7Fq+QvRN3cNjI1Qq40ijksIGtLqXqMJhIiI
        iE5BdGg0gSgCjFhEUQH5bCfipIYDhx7F4zv+Czt3/QRj5SqcBXLZ7Pj1vd0gWKkAUGD1OsEFl1pk
        s0C5NO0mERVxUqoNo5jt+ez163f/rDGF8exz7gZA9QZiQ//wf2Djzrc8UE/GLs5GPapan1bwcw7I
        FYAntynuu9NjbCwNg8a0H/5ELEJIUKnVAQUWL1yDNStfhsULLkYu24MkKaNaG4MPCYwRCKt8RERE
        M0JAgAaFNQ65bCdclEO5NIDd++/H1m3fwZ7922ANkG0EQdWps5dIumWsXAI6OoDLrrZYtkpQPY5q
        oEhGa/GgZFzHgxcs/ewlvV0/PZ6Bzr0AqN5CrD84/NWOn2y9cXPGYUnkZnlVP60l33wxXbd/4Cce
        T2xVZLPp+bztflvGWCQ+RrUawwiwZNEFWL/mBiyYdwEUAdXqCBJfa8wmsvwtIyIimslhMHiIIN0z
        mOuEKLBn/8N4ZOut2L33USiAQj4DY1xbFUGRtJm0VgNWrhFc8lyLTAaolKYbAq2PkxFbT7DruWtu
        XdfXdcNYMwudOwGw8Q33D986/66tr9mSz2S6rMn7oO01e2hjUGS+COzZqbjnDo/SGFAsonmiWjs/
        CIRQR6WawBpg2ZLLcP5zXoXe3tXwSR3V2jBCCAx9REREZ2YURAgKYwxyuS44E2H/wc145LH/wK49
        GxEA5LNpEJyqIigCQIFSCSh2AFdcY7FoqaBSOnLIQzuMOO9DxVbq9eGr1nxlbW/XjftPVwg89QHw
        SPhbc+eW12zOZSJjTT6o+rbWVFXTTl7ngI33BzzyUIDLpAOX2/tWDICAcrWGyABLl1yFtatfjjnd
        KxAnFdRqowACRBj8iIiIzgZpwDPIZ7tgbQaHBh/Ho49/Azt33wcNQC6XHc8HUwXBWi09OWT9RQYX
        XGqQJOlKZLshUMQGHyqmWo/D1Wu/sq6368atpyMEntoAeCT8rb5zy2u25jMRRPIebQ53Vk3n+pVL
        wE9+5LF/r6LY0Tivd8pvQyAiqNUq8AFYsngDLlj7OszpXoZ6XEKtXoJCObKFiIjoLBUQIBBkM53I
        uAIODT6Ohzd/Ebv3bYVzQDaTR5qLtGUIVAVKY8D8hYLnXmtRKKZzA9tfErZetWIr9RhXr/3Kmt6u
        Gx871SHw1AXAxjd2YOjWFXdtec0TuUwEK/m2T/ZQTTdh7t2tuPtHHvW4/Q5fEYvE11CtefTNXoQL
        1r0OC/o2oJ5UUKuNIT26l8GPiIjoXKCNk0Oy2U44m8Pe/fdj46NfxqGhg8hnLazNtrUsXKmkswev
        vNZi4WLB2Ng0KoGw3mvFVusxrlr7lZXzum/cfipD4KkJgI1Ol4NDty6+c8trduYzkWm38jdxv99j
        mwMevCcg4wCXabfqp6hUa4icwfo1N2DV8hemgx1rQ40fIIMfERHRORkENQAwyOdmQRV4bPu38Ohj
        /4nEA/lce9XApA7UE+DiKwxWrzPT3Bc4XgkMV6/9ytK+7ht3n6ru4JMfABuzbg4MfXXunY/euDuX
        ibLW5Nvr9lXAurSr9+H7Ah7bHJAvpufzTTXcW8QiSaqoxwFLFq7HhrWvQ0ehD5XqALxP2NxBRERE
        ANLOYWsj5PM9GBndh4cf/Tz2HXgc2Ux6AkmraqAYIPi0K3j1OoMLLzOI64BP0NY0YxHrfajYaj2u
        XX3+rYvndd9w6FTMCTypAVA1NiJRODzyLdy+6eX9hWx2rki2vcpfaJzeAeDuH3rs3aPoKLZ3gpuI
        QaVaQRRZXHj+67Fs8dWo1SuIkxIrfkRERDRJbgnIREVELo/tu27Hpi1fRvBANptvVAtbZA8AYyVg
        4SLBlc+3EKSnirQXO6xXrdlyrXboug3f7J0z66fGM9QZFwBVVUREvVbwnfvmPBxC5QLnujzaGPWi
        moY/nwB33OYxcFhRLAJhirsqEKh6VKsx+vqW46J1b0I+NweV6mBjWjjDHxEREU0uaIDAoJjrwWhp
        Px7afAv6D+9GPhdBxKX7BydhJB0VM3uO4JrrLaxrhMB2loPF+SQZtsbkN770ssMXWsmPZ6kzKAAG
        AYwmfhjff2jFf1TjgVfl3Ky2Gj5UgWwuPYfvjts8xoYV+cLU+/1EDOKkAu+B1StehOcsfym8L6Me
        V1j1IyIiomlpVgONi7B12zexbcePEDkD5zJolZ1EgEoZ6OhKQ2Az07QTAgXWV5MRm4tmf/1FF23/
        aWe7xjPVGRAAFc2RiT9+5Kq/OTD8k1/ryPYE1bqZ+sEGMjmgWlLccZtHpQrkcu2Fv1qtgkwmgwvP
        fxN6565BuToEVQ8D7vUjIiKi4wmBHsZEyGW7sO/gRmza+kUkSdIYFxNahsBqFcjngGuut8gVBfV2
        Q6Bkwlht0Mzreu6Hn7f+rl/H+BEXckK/txMfAFUtRPxDT/zCG7ft/8QtHbluVY1l6k8DshmgXFXc
        9QOPWhXI5ttp9kj3+3XP6sPF69+CbKYT1dowq35ERET07GMNAGhALt+NSnkAD2z+N4yVBpGbKgQa
        oFZJVzWveoFFISeo1dsNgZGOVYdk1fy3v+milR//fDNbzdgAqOqtiPUHBr+8/IebXre9mO9ofgGZ
        Kvxlso1l39s96hVFpo3KHxSo1muY37sK69e8FqoBccIlXyIiIjrBQVADMpkiNARs2vJ5HDj8FAq5
        bMusIgLUq0AmL7jmunQ5uM09gaoiUqqM4fkbvrRiXs9rdzQz1owLgKqJEXFhtPIIvnnPhoFiLtcj
        4gKgZsrwl0kPWr7zhx7ViiLbxow/RUCtHmPZ4suxctmLUY9LCD6GiPBZSkRERCchBCqsy8DZHB57
        4lvYs+9hZHJZyBQhsFYHcnnB1c+3iDLtHh0nQTUxpWp18OVXbJrdmV8/nrVmUAAMAhioBv3OffO+
        X60femEUdQVoMmX4cw6AAHfd7jE6osi1cbqHakA9jrF8yTVYft41qNZGocFP5wwWIiIiouNJgRBj
        kY1mYftT/4Und9+LbCbTsgAlAlQrQOcswVXXWUCBJGkjtogLcTxscpm5//XSyw68SMRIel7xs28K
        OQEBUAHAAuLv3fq6d+/Y/+W/68i31/QhJq3+3Xunx6EDinxxij1/AmgIiJMYK5deh4XzL0W9Ngzl
        05GIiIhOIRFBNtOFnXvuxM5ddyHKRC2PlRWTDoueO09w+dUW9frUfQ7p18mEscqgWT7/tf/z8jVf
        +gigFoB/tk0hzzoANsuRTx74x+V3bf6V7V3FbqjGU+77g6QbIzfeH7B7Z0Ch2F7lL45jrFx2HRbM
        uxjV6iDAM3yJiIjotKRAIJfpxq79P8HOp+5CNspCpVWYA8olYPFSgwsuNahV0c4JFyoSyXBpCFet
        +4cVy+b98o4TsRT8LANgOpsm9oP4jx/P3h1FmUUiGd9Ipy2CHFAoAtu2Bjy+OaDQ0caoF1XU4jqW
        LbkKC+ZdimptqGXSJiIiIjoFGRCZ7Czs2nsXdu25H5lstmUFTAQojwHPWWewao1BudTWfkCvWrdx
        XN/z088bWBzZHjzb+YDu+L9lReOAE3/XI6/4SAAWGVPwqvGU4S+XB/bvUzyxJSBXbGfOH1CN61iy
        8FLM77sQlcpAuhyMwGceERERnVaV2gAWzb8cIdSwZ98jyOVykw6LVgVyReCJLQEdswR98wTVylQh
        UK0xBR9QX3TXI6/4yPMvvOvdaQbT414KPu4KoGpiRZx/cv/HNty5+Zc3zip2Q0PrpV8FEGWAWlVx
        z489oICdMoIK6vUq5vWuxnkLr0U1GYVw0x8RERHNICKCKCpix1M/wOGBHchkcmi1vuuTNDFd8TyL
        bE4Q16eMciomkpHSEK5e948XLJv/zk3NLHYKA2Bj6Tcewtfu6tkV2WixSDYB1LV+cABrgfvu8iiN
        KTLZ1tU/gaCeVDGrYyFWLnsRkqSKoB4CdvsSERHRzKGqMMbCmgjbnvwuSuV+RC4HnSQEiqQzAYsd
        gsuusvC+jfnHkES15mIf7371VYNLoqgbx7sUfLwVQAMg3P7QVe8/MPiTm/PZ7qAaTznyJV8Atj4S
        sPvJkHb8tvzSgiSpIZftwIplLwM0IIRGXCYiIiKaeTEQxmSgGrBtx7cRJ2U4lwVahMBKCVi8zGDN
        eoNKeer9gCJRqNSGzLye59583UV3faCZyU56AFSNnUiU7DzwiQU/fvgX9s7qmLrrVzXt+D10QLHp
        AY9cYerwp5pAVbFy6YuQyXQiSaoMf0RERDTjQ6BzOVSqg9jx1G0wxk09I7AMbLjEYu48QW3qM4NV
        JJKRsSE878KPL1w67+37mtnsJAZAbdxV6H/eNe9HldrB50Vulgd8y8YP6wAfA/f/JIEP6fBnbflV
        BD6uYtGCK9DduRj1pMTwR0RERGdMCMy4IgaGd2DfgQfhosn3AwrSodDWAJc+18FGjf2BLVkfJyM2
        n+378SuvOnBtejOq08lK0+oCTs+hc37Tk+994fDYwed1FLp1qq5fEcBZYMvDHnGcVgJb30WBT6qY
        3bMMszoXohaPMPwRERHRGaUWj6C76zyUK/0YGd0D5yYPgVEE1KrA4496bLjEIky5H9DbTNStw2MH
        n7fpyfe+cMOyD/5XM6O1e/+mUQFMNxmGEOMLt2UOZFymTyTT8qzf5tLvgb0BWx8NyLdxzFvwMaKo
        gCWLroJ6P+nmSSIiIqKZTMQCAuzacycSX4MxrsXHApUKsOZ8g3kLTRtLwRJU66ae1A++4fr6PGMi
        TKchpO0KoKoYEfh7t/z8rwWPPpOZYuZf45zfelWx8wlFNmrc3dZfBSJA39x1QFAEjcHqHxEREZ2J
        VGNYU0Df7LXYc/B+CCK02gSXjYCdTyh6Ziuck/FRMZPcujGm4IOv99275ed/7cp1//7hZlZrK5y2
        UwFUTUTE6XDpIXzthxdrZ0cnVENAi3PYVIFsHnjskYDD/VOPfGku/XZ1LcXc7lWoJ2WGPyIiIjrT
        YyCcy+PwwFaMjO6FnaIruF4D5vQKVq83qE05IBpBxJjRsVG8+vkPSlfxovHMNtW9aqsCKLAWQPLg
        Y++62UWAqE0U3rUMf1lgsF9x+KC2se8PCCFBFOXRVVyIOB7Dsz2jmIiIiGgm8EkZXZ2LUa4cRlAP
        I2ayrIhsFjh8UDHYF9AzR1CrtQyBRtQmLoJ78LF33Xz9JT+6uZnZpsx2UwWt5oHDw2MP4Ws/vlg7
        CkVo+kmt+jjgHPDIgwHVytRdv4DA+xrmzl6LXLYHIdTA6h8RERGdHRTOZFGqHsLhwcdg7dRdwbk8
        sP5igyTBVCFKRUTGyiW8+nkPSlfHRePZrdUntXEQmzUAwgOPv+uD1gCikVfU7eSBMU2ve/coSmNA
        ro2u3xBi5LPdyGY6kSRlPk+IiIjorFIPZeSy3chlulCPx1o2hEQRUBoD9u9TLFw05WxAEY28NbAP
        PP6uD77gkh+9t5ndWua7VhXACdU/+9UfXZy0U/0zBvAB2PxQgGr631MJ6jG7ayUiV0DQhM8SIiIi
        OusYcagnJQwOb4ORqHU2CmnoW3eRgTXpf7cwXgW84doHXVfHRX6qKuAUFUBjAYT7ttz0O43qX6Ja
        n3zvXyO17t2uSOpHZv61/gYTFHLdiGwO3tf47CAiIqKzkkeCjC0gH3WhWh9pWQV0Np0NeGCPYukK
        QbXacnOcCKLEGrj7ttz0Oy+6/Md/3Mxwk37C5BXAdJZMEsr43HeLtWwmmxHYlp2/xgCJBx59OMCY
        qc+zA9LqX/espTASQad/lB0RERHRGcOIQeJrGBndlc4JbEE1rfydf6GBs1NWAYPCm1q9Vn/zS0pZ
        ZwpoNRewRSdvcCIm3rjtfW/3CTI2k/dBW+/9izLA3l2K4IHItVf9y2U70/CnMZ8VREREdFYL6hGZ
        DDKugHpSgpHJq4DGAEkMHNyrWLq8UQVs0RFsJe99Usts3Pa+t1+y+u8+0cxyx/rgSSqAjepfMopb
        vj9rT2SjhWJanPqhaaExiYGtmwOMba+HVzWgozAPYiJAWf0jIiKic4AxCL6GUvng1FVAAMEDa9YZ
        uCj98+QhS4KGuol9vPdNLxpZ5FwnJqsCumMHM29FTLJz/6eurtWwMNfRoUFrLYc+Wwfs26OAT/88
        ZfUPAZHLwhiLEGJOfSEiIqJzg/ewxsGaLFTraLG7DkbS0Nd/ULF4aXo6yOSRSY01HTpWHly4c/+n
        rl65+KY7m5nuGVFxkj2AFoD/yu2Lbi1X996QcZ2xwkctgiyCBx5/NEAlvbNTUXhko25ELoMQWP0j
        IiKic4cxBvW4gloyBoPWI1OCAqLAc843MFPsBRTYuJ6MRoXcwq++5ro9NzYz3dEf94wKYKNt2A+O
        3pcZGt17Q0e+A6qTn/qBANgonVrtPZDJTF39AwADBysOvnWUJSIiIjrreB/gbATvzZS5yRmgXgcG
        Dyv6FghCjEmLhgrvMq4DQ6N7bxgcvS/T03lZ/VgjYY4V7CyA8Mj2P3lXAKDiYtX65NU/m3b+Dg5o
        uvSbxs8pBBiTRYBPEyRPfSMiIqJzjKqBmAgaami1DKxIt9cNDihm9wnEplXBSQjExQGIHtn+J++6
        9qIv/XUz2z3tg56+BNxo/vBj+Nx3Onc5m1ksEk3e/BEAlwGGhxR7dimiDNoMcwprsoAY/vSJiIjo
        HE6BAb6dI3AFiOvAoiWCrm5B0nLroATV2CS+vvvNLx1d4mwHjm4GcU9PoulGwe17PrG6VMPi2Z1F
        hDB580fzvg4PatqW3HYlz6Qfqp4/eCIiIjqHSSPJTRGiNB0BMzyo6OqWKfKiGmuLGC7XF2/f84nV
        q89712NHN4MctQRsBQC27/nEO7IO0OBjVbRs/qhUgHI5nfvX/l4+5dw/IiIiIgAi7VXQIpdmrkol
        7blo1QyiwcdZh2j7nk+8Y/V573pvM+ONf80jS8BpadD7MXz6G50Hc9lsL6Y4+SOKgIP7FQOHFc7x
        B0hERER0MiUJMHuOoG++IG5dSwuAN9Varf+trxjts0ctA4/HtmZpcNvuf9lQi9Gbz+URQt1MdSfG
        RhTWtnfsGxEREREdP2vT7DV7rkzVPWyMyaMW13q37f6XDWuW/uqmicvAEwJeGuH29n/rbTb927j1
        rQLliiJO0j8TERER0cllDBAnaQZrI3/F1qTZbmLWA8YrgAoRFwPA/kPff30uY+B93LKmJwYojaY3
        xeofERER0akhkmawYrF1P633seQyBvsPff/1AN6bZj0FIGkFUDUxAHDg8G09w6XqivTsOG15OF2I
        gWpJWf0jIiIiOoWMSTNYmLKfVq1znRguVVccOHxbz8TM19wDaAGEvYe+daMRQFVadv9aC1TKitiD
        zR9EREREpzIA2nQZuFJV5AsCP3kVUFQlNoJo76Fv3ThvzvUfb2Y+BwDpsGfgiV3/+qZMBITgW46j
        EQDVSvqeq79EREREp1YzixUKaJnZQvDIRGnGu2TNn368mflcoyXY1+JBjJT2vzjK5KDqWy7/egUq
        FYWxTIBEREREp5qxaRbzKq1HSKu31uUwUtr/4lo8iGzU44EgTjUYEeP3939vea2GTD6TQ9D6pLHO
        GCCpAz4BLPf/EREREZ1y1qRZLKmn2/FaDIUWJzmM1aqZ/f3fW7504Rt2qAYzfn7HUwe+9kIxgApa
        7v9TkyZOVbD6R0RERHSaaGNFtqNLoC0CoApiMYieOvC1Fy5d+IYdAMQ1U9zw2GOvcKZxa632/wUg
        rqWVQOY/IiIiotPDmDSTSUDro4RV4Uya9QD8CyBwIjYBgAOH77o+ihx8SFqPfwlAnCgMO0CIiIiI
        Tl8AlDSThdB6H6APiY0ihwOH77oeAERs4gCgf+COYrWK3u7OAoImrff/+TQEcv4fERER0elMgGkm
        SzzgbKt9gCrOFDBWGuntH7ij2Dv7mpIDgMMjD68PAqiYoIpJo50CqNca+/8YAImIiIhOKw1pNrOF
        llVAUTEhCMzhkYfX986+5m4HAPsOfu/y9EgQeLQIgNC048QIV3+JiIiITjcjaTaDYop9gPAGMPsO
        fu/ytct++W4XQh2V+sGrrAUU2vJzA4AkASdAExEREc0EkmazKftAoOlJbvWDV4VQ/6hLfBn7+394
        UWSA4H3LWKeN/X+WJUAiIiKi08429gGqb/1xwXuJDLC//4cXJb4MFzQpGJNb5UMVimAmy4+CxhcI
        gHD/HxEREdHpJ2k2C0FhTKsqYDAQgTG5VUGTgtvX/4O+kVKl0N3RgaCTVwClkTAhgLD6R0RERDQj
        qDRWaC1aDIRWiWwRQ2NjhX39P+gzAnMe0g5gKCDNPYTHevOeDzIRERHRTOP95Pmt8SYq6SkeAnOe
        23fotvMaHcAJFG7yeNlY/mUFkIiIiGjGkMYycBudwIkB3L5Dt53nhke3LQcaJ8C1+CRVwCsfZCIi
        IqKZxmt7WQ4Ahke3LXfW5ua3U9BTTc+aM5YNwEREREQzhbFpRtM2CnUCwNrcfOdDvTdt8dXWZcPG
        hzD8EREREc0czRg35RJwI8j5UO91+/pvm5uNInhN2hruwv1/RERERDOL6tT5z2tislGEff23zXXe
        x7MFDlMcAtKirZiIiIiITnsI9JhqqVYFDt7Hsx0g3Y3kZ6b4DBgOgCYiIiKacUSAMPVBbY0kJ90O
        ilx7sbLxxiVgIiIioplFkR4I3F5OyzkFMu3eLlgBJCIiIpp5ZMpe3okyDoroyKe2ToAs/hERERHN
        UFMnwGaUi5wC2bZvkwmQiIiI6AzNf+OyEyuAbUVGIiIiIpp5pP0UGDmd9i0TERER0UwznUznpvPR
        HAJNRERENEMD4DQyndM2h7uIgBVAIiIiojM/BKqDoga0NwuQFUAiIiKiGRz+2guANadA3G4AZAWQ
        iIiIaIYGwLbzH2IHRX3C57WMeMZMb32ZiIiIiE4+EcAnUybAZtarOz0SAFt/xvQmTBMRERHRKdI8
        Ca7NsFZ3gJTbGh0dAMMQSERERDTjiKRZrb2cJmXjQ31AIVCFqqZLvMd6C0x+RERERDNWaJHjGm+q
        EPhQH3AdhSUDI2M74Ww+AMFMdqPNvX/sBCYiIiKaeVSnymkmJEnFzOpYOmD65lzeX68HCOxUqZGI
        iIiIZnAAbPUmsKjXA/rmXN7vQoj7FUh7QnTqGzaGDzARERHRTBJCGx/U6OUIIe533tf3hDB1lS8E
        IHjAuTa/CBERERGddMYASZzms1aFOtX0Y7yv73GL579o+6NP/CcATFnba64tcx8gERER0cwg0vZW
        PaMKLJ7/ou2us7hkV1wHoGJUJx8G3UyNRERERDSztLGaq1AxcR3oLC7Z5Qr53l1RBPgw9Txo7wEY
        QNgQQkRERDQzmEZGmyrHhTqiCCjke3e5+XOvGCjk8oeSpDLX2qIC4ZgVQJH0xsULh0ETERERzRDi
        Ae91iqVgo96XpJDLH5o/94oBF0ISC3SLBlwLpwGqk+4F9B7wKjAOUC4HExEREZ3e8GfSM4C919aT
        WkSDBhgxuiWEJHbZTBeWLnnFvRsf/fK13RmnXidfCtYABK9wTsD8R0RERHR6GQCJ17Qw16JJ14rT
        0Sqw6vxX3JvNdMEBAmeLdyWazoZpubwrQOKBjLT+IkRERER0CjSyWXPG32QUQKKAs8W7AIEDgDXL
        XvvQXfd/GlC4qT47rgGmA9wHSERERHSaGUmz2ZRVPIXzcZr5AKQBsLtr9RbjAB9iaRQCjz0KRoB6
        rAgqrAASERERnWZB02ymrSuA6kMsxqWZrxkAZW7PBu3pzG6px5W1kSt4ILhjpkykp4HwRBAiIiKi
        08sYIEnSXGYMWiRA4+tJ2fV0ZrfM7dkAAOJCSKwxLlk47/rvPvrEt9dmM05bzQQMAajVFS4rXAcm
        IiIiOl0sUCsrQki7gSf9MOO0UgOWLb7+u2mWS+x4pa9v9vpvbnrs2++Gwky1D7BeBWZ1Mv8RERER
        ncb8h3oV7ez/M96nWa/5Vw5IJ7qsWvbaH37nx38NDcG2OhIOFqhVFT5wHyARERHR6eJDmslgWx8B
        pyFY79Os1/i74MRYBYDF858/UixgX92XF1iT1bTl45kMgCRO3zLZdN2ZiIiIiE4dY4F6Lc1j1rX6
        SNG6L0uxgH2L5z9/BADEWHUCUVUfidh4Yd8lX9+5+4F3dHZYH0Iy6WpyUKBcVuTywkYQIiIiolMd
        AE2axYICRlt9nPWVSjBLF1/ydQBoZj4HAOlgF4uL1v7Svz+2/aZ3zII1QDJ5ljRApazAHIFwGZiI
        iIjolKuUtWXzBwAIrKnVgYvW/tK/T8x8Lv1H8QCwZOELvgcA3se21TxAI0CtmpYeowzHwRARERGd
        KsakGaxWBewU+/+8j+3EjNfMfGkAFKcAzNye88Oi+Ut+ODi06/n5bNEH+ElXlVWBckkxuyDQmD8M
        IiIiolPBOmB4UFsFvzQowvpKreQWzV/yw7k95wOAEXEh/beGEBoJcf51t5SrAIxV1TToHetNBBgb
        bRw+TERERESnhIY0g4lMntNU0yxXrqbZbmLWAxoVQABQhQeA9avf8qk77vvM3wEaodUysAGqVaBW
        A7JZLgMTERERnWzGpNmrWk1PZWuVEwGNgk+z3cSsB0yoABrrAgBZufRVw12z7P3V6iig4idNlukN
        YXRIYS0a0wSJiIiI6KQI6Z6/0SF9WhY7ZvVPxVero+iaZe9fufRVwwCkkfUATKgACgQhJM4YF69e
        ccM/3bfxy/8wuztS7+uT5kpjgJERxdx5AhOBy8FEREREJ4lEgPdp9mp99i9gbKSl0Qouu+CGfwIw
        nvHG//3poU49AFy89h2frMWAqkaqmHQvoBigXgdGRxTWgFVAIiIiopMhANakmateTzNYi/1/qqpR
        LU4z3cSM1/S01WNpLgMve2V5Ud/c28fGDl2Xa9UN3GgGGRpUzJ4j6SwazgUkIiIiOrFMuvI6NJg2
        f7Ss/sH6SnnULeqbe/vKZa8sAxCZsPzbuLkJARCCENLh0Beuffufj5UBMc626jCxFhgbBUpjgIv4
        8yEiIiI60VyUZq2x0SOz/yZfoXV2rJxmOQAIIXZyVIVO9KghMqpBRIzG9VG8/29nlTtyLm+MC3r0
        cvGEBFmPga4ewXkrBHENrAISERERnSgKRFngqe2K4UFFJpp8150AIYTEjFWTygd+daQQZTrHs93T
        AuUzPlGMqoYoynTGa5Zf+3dbt//ovV0duUnPBvYAjANGBhW1svBkECIiIqITyFigVk6zlnGAb3n2
        r/NjlapZs+Lav2uEv0jEPOPIjmPu7dPgvViD51/xB3/54OaXvberU6acCVgPwKF+xZLlgnoVrAIS
        ERERPVsKuAywb4/CByBjWk5dUYhElSrw/Cv+4C8nZrq2AmCzGWTFeS89uKC3+3ujY0MvLhaK3odj
        N4OoT48lGTis6JsvcI5VQCIiIqJny1igVkkzlnVA8JN/rDXWj42NugW93d9bcd5LD+IYzR+tA2Da
        DGKNiZKXX//h933yi2+/t1gwDjr5VzUC1OrAwf2KpSsENVYBiYiIiI6fAlEG2LtbkcTpyWutz/81
        rlIF3viqD78PwHiWO2bW00luSaFodozc/NfyqABrncsnCp304BHVtPK37gKDKAuEhD87IiIiouNh
        HBDXgM0bA4xJR+9NRiBJklScAltu/g09/+gsdzTX4oYQQhwZE8VXXPjO933vjo/d2jvHGZ/Ek99R
        AeIEOLBPsXyVoJq0vrNERERE9EyqQOSA3U8qfAK4Kap/xjkzPAS8+Jp3Nqt/kTHRpKFt0gpg+sXT
        tuEkruAP/rpwMBvZXmszQaFm8uCYhsB1FxgUCkDCKiARERHRtDgHlMtp9S9yLec+QyDB+7qpxb7/
        D3+j3Oei/DFHvzzt9lt9cRGjISSRi/Lx8y676abv/uijn++d4+B93OpeAD5NrGsvlHRODBERERG1
        zTSqf/CNtNby3F+Hw4MVvOTam25yUR4hJNHEc3+PGde09W7CI4Ohkwr+4C8Lu7KRXWxtpuVeQJG0
        Y2XNesGcXkGtxqVgIiIioqmops0eh/sVWx9RZPOtl34Fknhfd7XY7/7D3yovidzU1T9gigpgGuaM
        hpC4yOWTay+/6Z3f+eFHv947x5lWVcDmEXG7dii65xhYAwTlD5WIiIioFWsAH4BdO0J65NsUY/WM
        debwYAUvff5N74xcHiEkzhg35Qa8KSuAaaALEDGoxyX83oc6tuezWG5tbsoqYLUCLFlmsHyVQbXC
        KiARERHR5HkLyOWBHdsCdj0ZkGur+ld1lRp2/PFvj63IRMXxzDYV084dEjEIIXGZqIg3vvKjbxka
        AUSchQKTvWkAMhlg91MBI0OKKIPWOxiJiIiIztn0l878GxlS7H4qIJNpVP9aZC0RZ4dGgDe+8qNv
        yURFhJC4dsIf0GYFML1fCklrePpHH+78Rqk89vJiruADvG31efU60NEpuPhyiyRmBiQiIiJ6RiAD
        4CLgwXs9xkYVmUzrjzewvlQt22Kh45u//2ujrwAgClVp8xQO0/4dEwT1AgBv/unP/Wy5CqgEqwpV
        TUuUx3rLZNLDi5/aMXUpk4iIiOhc01z6fWpHwMhgGv5aZStVqEqw5WqayQAgqBeZxhFsbjp30IgN
        qjCrV75ycMOaqz645fG73tvT1eF9iFueDpLJATufCOieLejqEdTZFUxERESUdv3m0rN+dz4RkMlN
        XSyzJvKDw2Nuw5qrPrh65SsHVWGM2DCtTDftO4pEAeDVL/nY+5IEY4mvO1UJrZKqSHqY8ZZNAcED
        1vEHTkRERGQdEHyakYxNM1Pr6p+ExNddkmDs1S/52PsmZrPpmHYUM+JU1dsFfRf6V77oPa/66rf/
        4rZ584omJAkmqzyqpuva5bJi6xaPCy6yqJRZBSQiIqJzV3Pm38aHPMplRX6qrXIKGGfNgQNV3PCy
        97xqQd+FUPXWiJv2sRvmuO6xGA9AXv7CD92+ZPHCL4yMlGCM860SawhALgfs26nY/WRAvsD9gERE
        RHTuhr98Adj9ZMC+nYpcLs1KrbKUMc6PjJSwZPHCL7z8hR+6HYA0Mtn0o5weZwoL6o0RGw70b8Qf
        /82F2tOdAWACWpwT3PyG4xi47GqL7h5BrcpKIBEREZ1b4S+bA4YGFffd6RFF7WQhCUAwg0N1/N6v
        Pyzzei8Yz2LHcx/M8d75tCHE23m9F+CVL3nP6w4ersMaKy3G1UABiEm/yYfvD4jrQBRNPeWaiIiI
        6KwIfyHNPnE9zUIiaTaaKj9ZY+Xg4Tpe+ZL3vG5e7wWNpV973AnquCuAwPhsQADAn/3ton/vH9z7
        5lmFYuI1abm3UASoVIHZcwRXXGMR19Oj4lgIJCIiorM2/AEwkg58vucOj4HDinw7Xb/ikpFyyfX2
        LPzc7/zqnp85OoMdD/NsvpGJswF/4S3f+JlKFQNxiJ1CQqsUGzTdD3ioX7HxgYBcLn1AiIiIiM5W
        RtL8s/GBgEP9jX1/OlX1T0IcYlepYuAX3vKNnwGmP/PvmBlOT0Anhqq3Itb/5IGPrv/Yp961acnC
        IrxPFFMU9USAcglYdb7B2g0G5TKrgERERHT2UQCFQjruZdujAYViW82waq2TXXtLeOfP//2G515y
        0yPNzPVs788JCYCNA94sIP6Tn3/Ne398363/Z/6cYkhC0laFsVIGNlxisOo5BmNjbAohIiKisyj8
        KdDRAWx7PGDTA+kklHY448L+wyXzvMtufN/b3viVDwJqAfgTUS47QQEQUA0iYlTV4/1/0XvraGnw
        hs5i0Xuf2HYemFoFuPhKg/NWGJQYAomIiOgsCX/FDuCp7QEP3h2QzbeXcax1frRUsp3Fnq9+4D39
        N4rY8ax1Iu7XCQuAABCCF2Os1mrD+M0PdO/O57Eom8l71dBeCKwBl15pcd4yYQgkIiKisyP8Pam4
        /26PbLa9bCNifK1esZUK9vzV+4cWZ7Nd4xnrRN23ExoA0xCYWGOcf2Trl/s++q+vO9DVlQVEArT1
        fEAIoD4NgZc9z2LJeQyBREREdGaHv11PKe77cSP8WTR2zbVMfwGqZni4hpt+8Uvz1q957cFmtjqR
        9++EB8D0m/ZGxIavf/e3XvS5r/3V985bWIAPfuqmEADep7NxLn2uxbIVwj2BREREdMaFv44O4Mnt
        ivt/4hFlAGunzn4A1BorT+0t482v/s0Xv+olf/n9ZqY60ffxpATAdDoNjEDCZ778c++4/c5/+6fe
        OQV4P3UIbFYCq1XgossNnnO+QXmsrQeNiIiI6LQSAIUO4PFHAx66Nx1111blD1BrrfQfLuO6q3/2
        l37utZ/5Z4UaAcLJmJFykgIgoKoQEQGgf/PPl//pI1vv+515vZ0+Seq2nQcvaKM7+GKDdRcaVEoc
        Fk1EREQzU3PIc74IbH44YNODabevkfaKWM5l/IH+Ubt+zWV/9uvvuPd3GxlN5SQtg560AJiGwLRb
        pVobwh/99Yp/HxwafPPsnqJPkqk7gyHpcSmVcjon8JLLDep1IEm4JExEREQzKPwp4ByQyQAP3JvO
        +csX0iPe2kl/zjk/MFiyPd09n/v939j+M7ls9wnt+D3lAbDxqAhEtB6XcPNfLvnW0NDgy3q6iiHx
        iWmrnCdAaQxYuFhw1bUWzgHVSuNBJSIiIjqd4S8AuXxaoLrrRx57dyuKHe0FPyjgrAuDwyXT3d3z
        7Zt/a9dPZaLieHY6mff75AdAHBkPU49LuPkvlvxgYGjw+jk9xSRJWp8ZPH4nGyeGzOoWXPMCg64u
        QanESiARERGdxvCnQLEIDA8r7vhBwMiQtnvCBwDAOZccHiy52d09t938nl0vyETFEz7u5bQGwEYI
        NMbY0AiBdw4ODV7V01VMEp+4diqBRoBKJS2xXnmNxdIVaQgMgUGQiIiITm3wMyYNfzu3K+6+wyNJ
        gHw+7VeY+gYAZ10yOFxyPd09d938nl1XN8KfMebEd/ye1gD4tBBYL+H9f7Hk7oGhwSvmtLsnEGnQ
        S5J0VuDaDQYXX2bgA1CvMQQSERHRqQl/mSxgDfDgfQFbNgVks2mBahqVP394sGRnd/fc84H37Loy
        kzm14e+UB8BnhMAPLfnO4NDgS3p6ipokSVsRTiR9gMtjQN8CwdXXWczqAsZKaaJmECQiIqKTEfwg
        QEcRGBkG7rzd4+A+RaHjSDZpM/zp4GBJerp7vvuB39710tMR/k5LADw6BP7Bh5Z8dmBo8Gfm9HRq
        ktSBNie9iKTNIDYCLrvSYtVaQa2WDpFmCCQiIqITGf6iDJDNAtu2KO6728PHafPHNGKUOpfB4cFR
        md3d8+9/+Nu73nK6wt9pC4BPD4Fj+P0PLv7Iwf7hd83rLcL7ZOph0RNCYJKko2KWrhJccY1FsQiU
        WA0kIiKiExD8IBjPFvfc4bFzmyJfmN6SLwC11smB/hL6erv+/o/eu/vdmUzHaQt/pzUANkKgGGM1
        9lV88paf/53b7vjCn87rzQFA0KnODj4qCJZKQCEPXHKlxco1giRO9woyBBIREdHxhL9sFnAR8MRW
        xQN3e5QraRicTnQSkQDAHOiv4vpr3vC7b3vTp/4ssrlT1u07IwNg+gCrSGPWzSc//7Ov/u7tn/3q
        nNkOkcsk3nvXbn4TA8RxeoTcoiWCy64y6O0TVMpAPUm7iJkFiYiIaNJMgrSLN+OAfAHoP6i4766A
        PbsUuRwQRencv3Zvy1qbxEndHR5I8JLr3nLD2974b187OvucswEwfSACRIwBEB565Etr/+ofX39P
        sQMdnYWOkPh4WiOfRYBKKQ2E519gcMGlBvkcUCoDIeEAaSIiIjpGFgmAcUCxAFSqwMb7Ax7dGKAh
        Pd5tunHJ2SiMlsdMaQxjv/nLX7ziovWv2wLAqIYgMyCMzIgAOCEuWwj8pi1fzf7zZ97yo+GR8uW9
        cwrw3iugbRfwjABJ4xi5jg7BhsssVp9vYY2iXEF6rDLLgURERAx+CsCk28h8EDz2qMem+zzGxhp7
        /Uybs/0mRCtrrfQfLqNrVuHed/zcZ6/dsPaGWjPjzJTve2YFQACqwYoYX4tH8bf/9OIPPvTIPb/d
        O9fCmIzX4O20vjlpLAuXgbl9gosvt1i6wkJEUakA3qeDHImIiOjcEgJgbTq8WVWwc7vHg/d6HDqo
        yBUay73TjEhirA+hbvsPeVy0/ooP/eovfe+92ahzPNvMpO9/xgXA9IcSjDEmAMCXvv6bL//at/76
        G7k80FkshiSJBdPZztfY+1erpmGwb4Fgw8UWy1alQbBaTjuJjWFVkIiI6GymmgY/54BcIQ1+T27z
        2PRgOtMvioBsrnGM7/TikToX6WipZKoV4NU/9RuveN2r/uqbR2caBsC2fkhBRIwACJse/WrPP33m
        Z74+OFy5eu6cLAB4DTq9aqBJf5i1ShoEexcILrjIYtlzLCKrqFbTGYIKVgWJiIjOJiGkxaAoA+Ry
        QOwFTz7usfEhj/5m8MsDkPabPI7kC/EA7KHDNfR05e/8pZ/791dtOP+GQaT7/VTEzMigNWMD4PgP
        Tb0xYoP3NfzLZ9/6a7fd8YW/6eoC8tmi92mDyPTqdo2KYLURBGf3CtasM1i51qCzU1Cvp9XCENK9
        hGwdJiIiOgNpunfPmLSql8kAo6OKJ7YEbN0cMNCfBr9c/rgqfgCg1kahUivZ4WHg+mve8Ov/7S2f
        /rC12fHsMpMfnhkfANPkfmRQ4v0Pf37pR/7fm74WgAtmd2WhYqa9NxDNXCfprMB6BSh2ClY+x2DV
        OoO+eQZGFNUaENdYFSQiIjpTjFf7skAuCwQVHDwQsG1zwBOPB5RGFZl8OuMPejy5L93rJxrswHAN
        Btj47v9+y6svvfCNO4/OLAyAJyLIq0IgFgI/MrofH/vka9638ZGf/Hm6N7AAH3wAdPoxTQCDdFZg
        tQIYq+jrM1h5vsHylQZd3QIfgHoVSOLGqwmg8T9ERER0ehMfEJCu2rkIyOQAa4DhIcWOJwKeeDTg
        4MGA4AW5fDrjLwDHl/wgwRprRktlVCvABeuf+7/e+bav/J9ZnfMBhVWolzOkoeCMCYBHkv2RzZQP
        bvrynE9/4X98et+BQy/v6QYymULifWJxnAu3xqSvHJr7AQt5xaKlFstXGixcIujsTG+2XgPqcfqx
        zc8jIiKiU5UFjlx/MxGQyab/PTqq2LsrDX57dnqUKzK+7695jT9Oaq3z9XrZDQ4BC+bN/eZb3/B/
        33rxhtcePjqbnCnOuAAIPL1BBAC+8LXfeNU3v/83n4hjzJndk4WIfdZBEAokPg2DwQO5gmLBIotl
        qwwWLBJ0dRs4p0iSNCwmydOfWAyFREREJy7sNa+tzqXNHM4BSSIYHgrYt0fx5LaAfXs8qmWBsWno
        c40k8GyDn6p3A4M1RBEOv/xFv/72N7z6r7/evEszudHjrAuAR54UR9bZR8cO4qP/+urffuiRu/9P
        JoL0dOehQBLS/YHHXY81Jq0S+/hIGMzkFD2zDRYuNli8VNDbK8h3GFinQADqzUDoj3rSSTpqRib8
        NxER0TlLj7xTxdOWZY0BjE2DXiYDwAA+EVTGAvr7Fbt3KvbuDhgcCKhXj4Q+G6WX1/Ds6nFqjPUC
        uMGhCuox9KL1V77vpl/82oc6O/qekUHORGd0AGw+bULw1hjnAeDJXfdmbrn1V//qngfufFdPF1As
        FqCqzzoINp+MQBru4jhtEIGk1cGeHoO58wTzFxjMmSfonGXSQ6StIijgQ3oUnW+EwuYbERHRucqY
        I2/WpkexWdM40csLajVgdCTg8EHF/r0Bhw4oBgcDqmUBNG30iKI0JAIn5LqaBj8RVyqVMTgMXHHJ
        1X//phv/9jeXLbm8nn6NxBpj/ZlexTkLAmDjJ5YuC1sACQDcfsdH53/12zf/5VO7+392VgdQKGRg
        jIu9T9yzDYKQIyNiNKShLq4DcQKoB6KMIl8wmNWl6O5JA2FXl6DYISh2AJmsgYsAazWtMDZe9ehR
        r4ae/gciIqIzKWE87d34GLbmalgIgPeCJAbqtYDSGFAaUwwPKw4fUAwNBowMCyrlgLguEAtEjeVf
        a4/M9w16Qq6Vaq1LQkiicrmOkTHgvMW9/3bDy27+reuuuWl/42OcavBn4nLvWR0Am7xPxFo3vj/w
        9jv/YcFXv3nzn+w7cPAXjQV6urIwxnrvvRxX13CLVzFNIaRVQh+n+wibr0hcpOn08bxBsajIZg0y
        OSCXE+QLRzqXjJPGe64SExHRGVqYQWPlKwAh0fGJGpUyUK0q6lWgVgsolQTVSkCSAOlhX429fjZd
        znXumdfYExiDgrVWQ/B2cLiG4IEF8/r+9YaX3/y/r7v6V/Y1L/HeJ2qtO6sC01kXAI88QWJjTIRm
        ENyx6965t3zlVz/wwMY7bxIDdHcC2WxRQwj+RCwPH/2qR9A4Wk6O/CZMXPr1/sgewYl7H1j5IyKi
        s8rESuCEvfDNPX7WPn0peOJ1U/W4hzS3zKbGWG+MsbVaSYZG09W8Sy64+qNves3fvn/5kssPNYNf
        CDGMic7KDVtnbQBsPnu898ZadyQIPnW3+8b3/uxXH9j4lfcMD2PBrE6gWMwDkNh7b09kVbAVdgkT
        ERGdyv3wEqy1HtCoVKpgZBTo6sK+Sy54zV+84sW/87fLz7syaV6ivU9grQ1n8zrcWR4AJwRB9caK
        EwAeAMrlQdz6zfe//N6Hbvlf2588cH0+B8zqBLKZIlQ19uHUhUEiIiI6SaEvbeqIavUSRkaBShVY
        sWzebZdf9KY/v/HlH/hmodDT/GDrNVErZ3fwO8cC4BFeExE1zhgTN//uoUe+Nveue//1HXff/+V3
        Do1gWbEAdBQNnMsDR8IgTwYmIiKa2RQQtcZ6iERJUsFYKaBUBrpn4ckrL33tx666/Bf/+aL1r24u
        8yKEEKmExIo7pwLRORcAx58hGkTVW2Mij8buglJpAHfc++kNP7nvU+947Il731ypYH4+D+RzQDZb
        AGBiVS8hhGYgJCIiotMcZYwxXsQqEKJarYxKFahUgHwe+1evvPxzz73s5//5msvfuqlYnD3+SSHE
        VsSeNV29DIDH8WLBe29EjJ1YFRwZPYh7Hvzchjvu+fjPP7nr/p8dHcViI0ChAORzFtbmAEgzEBpW
        CImIiE7BRTsNfCENfBp5X0Wl6lEupyNhOjuxe9mSS//tmit+4VNXXPzmTbM6+8Y/OYQQqQZ/tu/v
        YwCc7rNKg4TgrbWRAIgn/tumLf+5+I6f/Msrt+388ev3Hdj/okoFLnJpdTCTATKZAgQmUUAZComI
        iE5s2BNAFMHV62XU6+levjgB8nkkC+bN//6qpc/74jXP/W//uWHtK3cfdTuR93FjwLNh6GEAnDoM
        NpaInxEGx0qHsPWJH17ywMOfu+6xJ2572cDg/muGx9BtkLaz53JAJhJkM3kgfbI1lpkDQgjNQGhC
        gDSak8GgSERE506wAwADY9JxgQBgjFHANK+HFhqkVq+gHiuq1cb4NABdHRia3TP/jtUrr//2JRe+
        +fY1K5//QEdx7tFfIwoh1nN5iXfKABjHMRgCp3yuSgheAFjncsFa8RP/NUkCHn3s230Pb/7a1f2H
        dly9a+99lx7sP3jh0AjmAYAzR+Yd5fPpn5szkDKZCHpkO2HzF6E5yJo/GCIiOqNzBtJUp4336ThA
        UdTr8fgs3BDSPXvN+bhJozbSPQsH+nr7Hl6y8LL7e+cuv/PCda++8/zVLzvo3NOHdHivNkmqBoA3
        xiogvH62+qGIsAL4LJ7QdkJQ88f6oIAdFsD5jzz+raX79297jo3cuoc33boqhGSJMW5OvV7uGRzZ
        C2scJlQCiYiIzmIGPiTombUQmUxhMITksDFu14Ubbtzm42Tz/PmrHl//nJ/aCeBRg+V+khuxE4Ll
        eDMnTSPIvPGNb0S5XOYjcZwaAVpUk2YohLVZdS6b5LNdcC4DGAsn6ajzQ4e2p2cJG4eh4T14/Im7
        XJSxczTobABZADkAmQlvXBomIqIz8hIJoD7hrQqgJkYG4ro//JyVVyXdXYsQQgIoMHfuCiAEJJoe
        lZUkdVRqw0iSmvO+1rwWeknHtagIL4/Hq1AoMFyczHA94VWKHPULkfDhISIiGueOca30E/5MJzqk
        OOfAFH0KXw4dWXIXIMCnnSDNPRLHCpBERERn9KXvqP8OCqg1pnnpS5fSmEVORxYhIiIiIiIiIiIi
        IiIiIiIiIiIiIiIiIiIiIiIiIiIiIiIiIiIiIiIiIiIiIiIiIiIiIiIiIiIiIiIiIiIiIiIiIiIi
        IiIiIiIiIiIiIiIiIiIiIiIiIiIiIiIiIiIiIiIiIiIiIiIiIiIiIiIiIiIiIiIiIiIiIiIiIiIi
        IiIiIiIiIiIiIiIiIiIiIiIiIiIiIiIiIiIiIiIiIiIiIiIiIiIiIiIiIiIiIiIiIiIiIiIiIiIi
        IiIiIiIiIiIiIiIiIiIiIiIiIiIiIiIiIiIiIiIiIiIiIiIiIiIiIiIiIiIiIiIiIiIiIiIiIiIi
        IiIiIiIiIiIiIiIiIiIiIiIiIiIiIiIiIiIiIiIiIiIiIqJzy/8HKJ+MNpg3IEAAAAAASUVORK5C
        YII=
    </Bmp>
    <BkgAlpha>255</BkgAlpha>
    <Text>
      <v>=Money ((sum({&lt;Contabilidad.CUENTA_N2 = {'22'} , Contabilidad.FECHA = {$(vMesMayorSeleccion)}&gt;}Contabilidad.SALDO_FINAL))*-1,'$ #,##0', '.' , ',') &amp;' CxP Proveedores'</v>
    </Text>
    <ImageRepresentation></ImageRepresentation>
    <AllowVerticalScrollBar>false</AllowVerticalScrollBar>
    <AllowHorizontalScrollBar>false</AllowHorizontalScrollBar>
    <ActionItems></ActionItems>
  </Layout>
  <PrintSettings></PrintSettings>
  <UserSized>true</UserSized>
</TextObjectProperties>
